[{"code": "1607011016", "name": "Mariana"}, {"code": "1607011021", "name": "Mariana Ilir"}, {"code": "1607012001", "name": "Sungai Rebo"}, {"code": "1607012002", "name": "Sungai Gerong"}, {"code": "1607012003", "name": "Merah Mata"}, {"code": "1607012004", "name": "Perajen"}, {"code": "1607012005", "name": "Cinta Manis Lama"}, {"code": "1607012008", "name": "Perambahan"}, {"code": "1607012011", "name": "Pematang Palas"}, {"code": "1607012012", "name": "Tirto Sari"}, {"code": "1607012014", "name": "Pulau Borang"}, {"code": "1607012025", "name": "Perambahan Baru"}, {"code": "1607012028", "name": "Duren Ijo"}, {"code": "1607022001", "name": "Sungsang I"}, {"code": "1607022002", "name": "Sungsang II"}, {"code": "1607022003", "name": "Sungsang III"}, {"code": "1607022004", "name": "Sungsang IV"}, {"code": "1607022010", "name": "Teluk Payo"}, {"code": "1607022013", "name": "Tanah Pilih"}, {"code": "1607022015", "name": "Perajen Jaya"}, {"code": "1607022016", "name": "Rimau Sungsang"}, {"code": "1607022018", "name": "Marga Sungsang"}, {"code": "1607022019", "name": "Muara Sungsang"}, {"code": "1607031008", "name": "Kayuara Kuning"}, {"code": "1607031009", "name": "Mulia Agung"}, {"code": "1607031012", "name": "Pangkalan Balai"}, {"code": "1607031023", "name": "Seterio"}, {"code": "1607031033", "name": "Kedondong Raye"}, {"code": "1607032006", "name": "Langkan"}, {"code": "1607032007", "name": "Pangkalan Panji"}, {"code": "1607032010", "name": "Lubuk Saung"}, {"code": "1607032011", "name": "Ujung Tanjung"}, {"code": "1607032013", "name": "Sidang Mas"}, {"code": "1607032014", "name": "Galang Tinggi"}, {"code": "1607032015", "name": "Petaling"}, {"code": "1607032016", "name": "Rimba Alai"}, {"code": "1607032017", "name": "Pelajau Ilir"}, {"code": "1607032018", "name": "Regan Agung"}, {"code": "1607032019", "name": "Suka Mulia"}, {"code": "1607032020", "name": "Tanjung Agung"}, {"code": "1607032021", "name": "Tanjung Menang"}, {"code": "1607032022", "name": "Sri Bandung"}, {"code": "1607032024", "name": "Pelajau"}, {"code": "1607032025", "name": "Tanjung Beringin"}, {"code": "1607032026", "name": "Terentang"}, {"code": "1607032028", "name": "Tanjung Kepayang"}, {"code": "1607032034", "name": "Sukaraja Baru"}, {"code": "1607032037", "name": "Terlangu"}, {"code": "1607032038", "name": "Rimba Balai"}, {"code": "1607042002", "name": "Teluk Betung"}, {"code": "1607042004", "name": "Mukut"}, {"code": "1607042006", "name": "Sumber Rejeki"}, {"code": "1607042007", "name": "Dana Mulya"}, {"code": "1607042008", "name": "Wana Mukti"}, {"code": "1607042009", "name": "Budi Asih"}, {"code": "1607042013", "name": "Rukun Makmur"}, {"code": "1607042014", "name": "Nunggal Sari"}, {"code": "1607042017", "name": "Majatra"}, {"code": "1607042018", "name": "Wonosari"}, {"code": "1607042031", "name": "Sumber Mulya"}, {"code": "1607042032", "name": "Rawa Banda"}, {"code": "1607042037", "name": "Senda Mukti"}, {"code": "1607042038", "name": "Tirta Mulya"}, {"code": "1607042039", "name": "Banjar Sari"}, {"code": "1607042040", "name": "Buana Murti"}, {"code": "1607042041", "name": "Tabuan Asri"}, {"code": "1607051017", "name": "Betung"}, {"code": "1607051021", "name": "Rimba Asam"}, {"code": "1607051022", "name": "Betung Selatan"}, {"code": "1607052002", "name": "Pulau Rajak"}, {"code": "1607052003", "name": "Bukit"}, {"code": "1607052004", "name": "Sri Kembang"}, {"code": "1607052005", "name": "Lubuk Karet"}, {"code": "1607052014", "name": "Taja Mulya"}, {"code": "1607052015", "name": "Taja Raya I"}, {"code": "1607052016", "name": "Taja Indah"}, {"code": "1607052018", "name": "Taja Raya II"}, {"code": "1607052020", "name": "Suka Mulya"}, {"code": "1607061021", "name": "Jakabaring Selatan"}, {"code": "1607062001", "name": "Kebon Sahang"}, {"code": "1607062002", "name": "Siju"}, {"code": "1607062003", "name": "Tanah Lembak"}, {"code": "1607062004", "name": "Parit"}, {"code": "1607062005", "name": "Pelaju"}, {"code": "1607062006", "name": "Suka Pindah"}, {"code": "1607062007", "name": "Baru"}, {"code": "1607062008", "name": "Tanjung Kerang"}, {"code": "1607062009", "name": "Rambutan"}, {"code": "1607062010", "name": "Tanjung Merbu"}, {"code": "1607062011", "name": "Sako"}, {"code": "1607062012", "name": "Gelebak Dalam"}, {"code": "1607062013", "name": "Menten"}, {"code": "1607062014", "name": "Pangkalan Gelebak"}, {"code": "1607062015", "name": "Sungai Dua"}, {"code": "1607062016", "name": "Sungai Pinang"}, {"code": "1607062017", "name": "Sungai Kedukan"}, {"code": "1607062019", "name": "Durian Gadis"}, {"code": "1607062020", "name": "Pulau Parang"}, {"code": "1607072001", "name": "Muara Padang"}, {"code": "1607072002", "name": "Tanjung Baru"}, {"code": "1607072003", "name": "Karang Anyar"}, {"code": "1607072006", "name": "Purwodadi"}, {"code": "1607072007", "name": "Sumber Makmur"}, {"code": "1607072008", "name": "Air Gading"}, {"code": "1607072009", "name": "Tirto Raharjo"}, {"code": "1607072010", "name": "Daya Utama"}, {"code": "1607072011", "name": "Daya Makmur"}, {"code": "1607072012", "name": "Sido Mulyo 18"}, {"code": "1607072013", "name": "Sido Rejo"}, {"code": "1607072018", "name": "Sido Mulyo 20"}, {"code": "1607072037", "name": "Margo Mulyo 20"}, {"code": "1607072038", "name": "Margo Sugihan"}, {"code": "1607072042", "name": "Tirta Jaya"}, {"code": "1607082007", "name": "Marga Rahayu"}, {"code": "1607082008", "name": "Sumber Mulya"}, {"code": "1607082009", "name": "Sumber Hidup"}, {"code": "1607082010", "name": "Telang Rejo"}, {"code": "1607082011", "name": "Telang Jaya"}, {"code": "1607082013", "name": "Telang Makmur"}, {"code": "1607082014", "name": "Telang Karya"}, {"code": "1607082015", "name": "Panca Mukti"}, {"code": "1607082016", "name": "Mukti Jaya"}, {"code": "1607082019", "name": "Mekar Sari"}, {"code": "1607082024", "name": "Talang Indah"}, {"code": "1607082025", "name": "Mekar Mukti"}, {"code": "1607082026", "name": "Upang Jaya"}, {"code": "1607082027", "name": "Upang Karya"}, {"code": "1607082028", "name": "Upang Cemara"}, {"code": "1607082029", "name": "Upang Ceria"}, {"code": "1607091012", "name": "Makarti Jaya"}, {"code": "1607092002", "name": "Delta Upang"}, {"code": "1607092006", "name": "Pendowo Harjo"}, {"code": "1607092007", "name": "Pangestu"}, {"code": "1607092008", "name": "Tirta Kencana"}, {"code": "1607092010", "name": "Upang Makmur"}, {"code": "1607092013", "name": "Upang Mulya"}, {"code": "1607092017", "name": "Purwosari"}, {"code": "1607092019", "name": "Tanjung Mas"}, {"code": "1607092020", "name": "Tanjung Baru"}, {"code": "1607092021", "name": "Sungai Semut"}, {"code": "1607092022", "name": "Muara Baru"}, {"code": "1607101002", "name": "Air Batu"}, {"code": "1607101003", "name": "Sukomoro"}, {"code": "1607101004", "name": "Sukajadi"}, {"code": "1607101006", "name": "Kenten"}, {"code": "1607101022", "name": "Tanah Mas"}, {"code": "1607101023", "name": "Talang Keramat"}, {"code": "1607101024", "name": "Sukajadi Timur"}, {"code": "1607101025", "name": "Tanah Mas Indah"}, {"code": "1607101026", "name": "Rawa Maju"}, {"code": "1607101027", "name": "Air Batu Jaya"}, {"code": "1607101028", "name": "Sei Sedapat"}, {"code": "1607101029", "name": "Azhar Permai"}, {"code": "1607101030", "name": "Keramat Raya"}, {"code": "1607102001", "name": "Sungai Rengit"}, {"code": "1607102005", "name": "Pangkalan Benteng"}, {"code": "1607102007", "name": "Gasing"}, {"code": "1607102019", "name": "Talang Buluh"}, {"code": "1607102020", "name": "Sungai Rengit Murni"}, {"code": "1607102021", "name": "Kenten Laut"}, {"code": "1607112001", "name": "Muara Abab"}, {"code": "1607112002", "name": "Tanjung Pasir"}, {"code": "1607112003", "name": "Tanjung Tiga"}, {"code": "1607112004", "name": "Rantau Bayur"}, {"code": "1607112005", "name": "Pagar Bulan"}, {"code": "1607112006", "name": "Kemang Bejalu"}, {"code": "1607112007", "name": "Tanjung Menang"}, {"code": "1607112008", "name": "Srijaya"}, {"code": "1607112009", "name": "Sejagung"}, {"code": "1607112010", "name": "Sungai Pinang"}, {"code": "1607112011", "name": "Semuntul"}, {"code": "1607112012", "name": "Lebung"}, {"code": "1607112013", "name": "Lubuk Rengas"}, {"code": "1607112014", "name": "Paldas"}, {"code": "1607112015", "name": "Tebing Abang"}, {"code": "1607112016", "name": "Talang Kemang"}, {"code": "1607112017", "name": "Rantau Harapan"}, {"code": "1607112018", "name": "Penandingan"}, {"code": "1607112019", "name": "Sungai Naik"}, {"code": "1607112020", "name": "Sungai Lilin"}, {"code": "1607112021", "name": "Sukarela"}, {"code": "1607122001", "name": "Telang Sari"}, {"code": "1607122002", "name": "Mulya Sari"}, {"code": "1607122003", "name": "Purwosari"}, {"code": "1607122004", "name": "Sri Menanti"}, {"code": "1607122005", "name": "Sebalik"}, {"code": "1607122006", "name": "Tanjung Lago"}, {"code": "1607122007", "name": "Kuala Puntian"}, {"code": "1607122008", "name": "Sukatani"}, {"code": "1607122009", "name": "Sukadamai"}, {"code": "1607122010", "name": "Banyu Urip"}, {"code": "1607122011", "name": "Bangun Sari"}, {"code": "1607122012", "name": "Sumber Mekar Mukti"}, {"code": "1607122013", "name": "Muara Sugih"}, {"code": "1607122014", "name": "Manggar Raya"}, {"code": "1607122015", "name": "Bunga Karang"}, {"code": "1607132001", "name": "Margo Mulyo 16"}, {"code": "1607132002", "name": "Rejo Sari"}, {"code": "1607132003", "name": "Daya Murni"}, {"code": "1607132004", "name": "Daya Bangun Harjo"}, {"code": "1607132005", "name": "Sumber Mulyo"}, {"code": "1607132006", "name": "Sugih Waras"}, {"code": "1607132007", "name": "Indrapura"}, {"code": "1607132008", "name": "Cendana"}, {"code": "1607132009", "name": "Argo Mulyo"}, {"code": "1607132010", "name": "Tirta Harja"}, {"code": "1607132011", "name": "Tirta Mulya"}, {"code": "1607132012", "name": "Daya Kesuma"}, {"code": "1607132013", "name": "Margo Rukun"}, {"code": "1607132014", "name": "Ganesha Mukti"}, {"code": "1607132015", "name": "Timbul Jaya"}, {"code": "1607132016", "name": "Jalur Mulya"}, {"code": "1607132017", "name": "Gilirang"}, {"code": "1607132018", "name": "Juru Taro"}, {"code": "1607132019", "name": "Kuala Sugihan"}, {"code": "1607132020", "name": "Beringin Agung"}, {"code": "1607132021", "name": "Mekar Jaya"}, {"code": "1607132022", "name": "Sido Makmur"}, {"code": "1607142001", "name": "Air Solok Batu"}, {"code": "1607142002", "name": "Sri Mulyo"}, {"code": "1607142003", "name": "Srikaton"}, {"code": "1607142004", "name": "Sidoharjo"}, {"code": "1607142005", "name": "Bintaran"}, {"code": "1607142006", "name": "Damar Wulan"}, {"code": "1607142007", "name": "Enggal Rejo"}, {"code": "1607142008", "name": "Saleh Jaya"}, {"code": "1607142009", "name": "Saleh Agung"}, {"code": "1607142010", "name": "Saleh Mulya"}, {"code": "1607142011", "name": "Saleh Mukti"}, {"code": "1607142012", "name": "Saleh Makmur"}, {"code": "1607142013", "name": "Upang"}, {"code": "1607142014", "name": "Upang Marga"}, {"code": "1607152001", "name": "Bentayan"}, {"code": "1607152002", "name": "Teluk Tenggulang"}, {"code": "1607152004", "name": "Suka Mulya"}, {"code": "1607152005", "name": "Suka Raja"}, {"code": "1607152006", "name": "Karang Anyar"}, {"code": "1607152007", "name": "Karang Asem"}, {"code": "1607152008", "name": "Marga Rahayu"}, {"code": "1607152009", "name": "Sido Mulyo"}, {"code": "1607152010", "name": "Keluang"}, {"code": "1607152011", "name": "Bumi Serdang"}, {"code": "1607152012", "name": "Karang Mulya"}, {"code": "1607152013", "name": "Suka Karya"}, {"code": "1607152014", "name": "Panca Mulya"}, {"code": "1607152015", "name": "Suka Jaya"}, {"code": "1607162001", "name": "Talang Ipuh"}, {"code": "1607162002", "name": "Durian Daun"}, {"code": "1607162003", "name": "Lubuk Lancang"}, {"code": "1607162004", "name": "Biyuku"}, {"code": "1607162005", "name": "Bengkuang"}, {"code": "1607162006", "name": "Rimba Terap"}, {"code": "1607162007", "name": "Sedang"}, {"code": "1607162008", "name": "Tanjung Laut"}, {"code": "1607162009", "name": "Air Senggeris"}, {"code": "1607162010", "name": "Meranti"}, {"code": "1607162011", "name": "Sukaraja"}, {"code": "1607172001", "name": "Mainan"}, {"code": "1607172002", "name": "Santan Sari"}, {"code": "1607172003", "name": "Limau"}, {"code": "1607172004", "name": "Rejodadi"}, {"code": "1607172005", "name": "Lalang Sembawa"}, {"code": "1607172006", "name": "Muara Damai"}, {"code": "1607172007", "name": "Pulau Harapan"}, {"code": "1607172008", "name": "Purwosari"}, {"code": "1607172009", "name": "Limbang Mulia"}, {"code": "1607172010", "name": "Sako Makmur"}, {"code": "1607172011", "name": "Pulau Muning"}, {"code": "1607182001", "name": "Terusan Dalam"}, {"code": "1607182002", "name": "Karang Anyar"}, {"code": "1607182003", "name": "Muara Telang"}, {"code": "1607182004", "name": "Terusan Tengah"}, {"code": "1607182005", "name": "Sumber Jaya"}, {"code": "1607182006", "name": "Karang Baru"}, {"code": "1607182007", "name": "Muara Telang Marga"}, {"code": "1607182008", "name": "Terusan Muara"}, {"code": "1607182009", "name": "Talang Lubuk"}, {"code": "1607182010", "name": "Sri Tiga"}, {"code": "1607192001", "name": "Cinta Manis Baru"}, {"code": "1607192002", "name": "Sido Makmur"}, {"code": "1607192003", "name": "Sidomulyo"}, {"code": "1607192004", "name": "Nusa Makmur"}, {"code": "1607192005", "name": "Rimba Jaya"}, {"code": "1607192006", "name": "Teluk Tenggirik"}, {"code": "1607192007", "name": "Sebubus"}, {"code": "1607192008", "name": "Padang Rejo"}, {"code": "1607192009", "name": "Kumbang Padang Permata"}, {"code": "1607192010", "name": "Muara Baru"}, {"code": "1607192011", "name": "Tirta Makmur"}, {"code": "1607192012", "name": "Panca Mulya"}, {"code": "1607192013", "name": "Budi Mulya"}, {"code": "1607192014", "name": "Panca Desa"}, {"code": "1607192015", "name": "Air Kumbang Bakti"}, {"code": "1607192016", "name": "Sebokor"}, {"code": "1607202001", "name": "Karang Sari"}, {"code": "1607202002", "name": "Maju Ria"}, {"code": "1607202003", "name": "Sri Agung"}, {"code": "1607202004", "name": "Sumber Rejeki"}, {"code": "1607202005", "name": "Tabala Jaya"}, {"code": "1607202006", "name": "Jati Sari"}, {"code": "1607202007", "name": "Mekar Sari"}, {"code": "1607212001", "name": "Penuguan"}, {"code": "1607212002", "name": "Sumber Rejo"}, {"code": "1607212003", "name": "Sumber Mukti"}, {"code": "1607212004", "name": "Sumber Agung"}, {"code": "1607212005", "name": "Wonodadi"}, {"code": "1607212006", "name": "Mekar Sari"}, {"code": "1607212007", "name": "Songo Makmur"}, {"code": "1607212008", "name": "Karang Manunggal"}, {"code": "1607212009", "name": "Purwodadi"}, {"code": "1607212010", "name": "Ringin Harjo"}, {"code": "1607212011", "name": "Bumi Rejo"}, {"code": "1607212012", "name": "Kelapa Dua"}]