[{"code": "3573011001", "name": "Balearjosari"}, {"code": "3573011002", "name": "Arjosari"}, {"code": "3573011003", "name": "Polowijen"}, {"code": "3573011004", "name": "Purwodadi"}, {"code": "3573011005", "name": "Blimbing"}, {"code": "3573011006", "name": "Pandanwangi"}, {"code": "3573011007", "name": "Purwantoro"}, {"code": "3573011008", "name": "Bunulrejo"}, {"code": "3573011009", "name": "Kesatrian"}, {"code": "3573011010", "name": "Polehan"}, {"code": "3573011011", "name": "Jodipan"}, {"code": "3573021001", "name": "Klojen"}, {"code": "3573021002", "name": "Rampalcelaket"}, {"code": "3573021003", "name": "Samaan"}, {"code": "3573021004", "name": "Kiduldalem"}, {"code": "3573021005", "name": "Sukoharjo"}, {"code": "3573021006", "name": "Kasin"}, {"code": "3573021007", "name": "Kauman"}, {"code": "3573021008", "name": "Oro-oro Dowo"}, {"code": "3573021009", "name": "Bareng"}, {"code": "3573021010", "name": "Gading Kasri"}, {"code": "3573021011", "name": "Penanggungan"}, {"code": "3573031001", "name": "Kotalama"}, {"code": "3573031002", "name": "Mergosono"}, {"code": "3573031003", "name": "Bumiayu"}, {"code": "3573031004", "name": "Wonokoyo"}, {"code": "3573031005", "name": "Buring"}, {"code": "3573031006", "name": "Kedungkandang"}, {"code": "3573031007", "name": "Lesanpuro"}, {"code": "3573031008", "name": "Sawojajar"}, {"code": "3573031009", "name": "Madyopuro"}, {"code": "3573031010", "name": "Cemorokandang"}, {"code": "3573031011", "name": "Arjowinangun"}, {"code": "3573031012", "name": "Tlogowaru"}, {"code": "3573041001", "name": "Ciptomulyo"}, {"code": "3573041002", "name": "Gadang"}, {"code": "3573041003", "name": "Kebonsari"}, {"code": "3573041004", "name": "Bandungrejosari"}, {"code": "3573041005", "name": "Sukun"}, {"code": "3573041006", "name": "Tanjungrejo"}, {"code": "3573041007", "name": "Pisangcandi"}, {"code": "3573041008", "name": "Bandulan"}, {"code": "3573041009", "name": "Karangbesuki"}, {"code": "3573041010", "name": "Mulyorejo"}, {"code": "3573041011", "name": "Bakalankrajan"}, {"code": "3573051001", "name": "Tunggulwulung"}, {"code": "3573051002", "name": "Merjosari"}, {"code": "3573051003", "name": "Tlogomas"}, {"code": "3573051004", "name": "Dinoyo"}, {"code": "3573051005", "name": "Sumbersari"}, {"code": "3573051006", "name": "Ketawanggede"}, {"code": "3573051007", "name": "Jatimulyo"}, {"code": "3573051008", "name": "Tunjungsekar"}, {"code": "3573051009", "name": "Mojolangu"}, {"code": "3573051010", "name": "Tulusrejo"}, {"code": "3573051011", "name": "Lowokwaru"}, {"code": "3573051012", "name": "Tasik Madu"}]